pixelscamp_api/__init__.py
pixelscamp_api/pixelscamp_api.py
pixelscamp_api-1.0.dist-info/DESCRIPTION.rst
pixelscamp_api-1.0.dist-info/METADATA
pixelscamp_api-1.0.dist-info/RECORD
pixelscamp_api-1.0.dist-info/WHEEL
pixelscamp_api-1.0.dist-info/metadata.json
pixelscamp_api-1.0.dist-info/top_level.txt
pixelscamp_api-1.0.dist-info/zip-safe
